MANIFEST.in
README.md
setup.py
tomcom/__init__.py
tomcom.buildout.scripts.egg-info/PKG-INFO
tomcom.buildout.scripts.egg-info/SOURCES.txt
tomcom.buildout.scripts.egg-info/dependency_links.txt
tomcom.buildout.scripts.egg-info/entry_points.txt
tomcom.buildout.scripts.egg-info/namespace_packages.txt
tomcom.buildout.scripts.egg-info/not-zip-safe
tomcom.buildout.scripts.egg-info/requires.txt
tomcom.buildout.scripts.egg-info/top_level.txt
tomcom/buildout/__init__.py
tomcom/buildout/scripts/__init__.py
tomcom/buildout/scripts/pin_version/__init__.py
tomcom/buildout/scripts/upgrade_version/__init__.py