Metadata-Version: 1.1
Name: tomcom.buildout.scripts
Version: 0.0.0.1
Summary: buildout helper scripts
Home-page: http://eggserver.tcis.de/tomcom.buildout.scripts
Author: tomcom GmbH
Author-email: kai.hoppert@tomcom.de
License: GPL version 2
Keywords: buildout helper
Platform: Any
Classifier: Development Status :: 5 - Production/Stable
Classifier: Environment :: Web Environment
Classifier: Framework :: Plone
Classifier: Framework :: Zope2
Classifier: Intended Audience :: Other Audience
Classifier: Intended Audience :: System Administrators
Classifier: License :: OSI Approved :: GNU General Public License (GPL)
Classifier: Operating System :: OS Independent
Classifier: Programming Language :: Python
Classifier: Topic :: Internet :: WWW/HTTP :: Site Management :: Link Checking
